{
  "timestamp": "2026-04-25T09:00:37.685Z",
  "categories": [
    "Coleccionismo",
    "Tecnología y electrónica",
    "Cine, libros y música",
    "Deporte y ocio",
    "Niños y bebés"
  ],
  "sections": {
    "Coleccionismo": {
      "total_items": 203,
      "new_items": 37,
      "items": [
        {
          "title": "Figura Funko Pop Hulkbuster",
          "price": 35,
          "city": "Barcelona",
          "url": "https://es.wallapop.com/item/figura-funko-pop-hulkbuster-1255845655",
          "reserved": false,
          "profile": "funko",
          "query_ebay": "Funko hulkbuster",
          "verdict": "skip",
          "reason": "0 reservados de 'Funko hulkbuster' (sin evidencia de demanda)"
        },
        {
          "title": "Funko Pop Kinder Joy Stranger Things Eleven",
          "price": 1.5,
          "city": "Argentona",
          "url": "https://es.wallapop.com/item/funko-pop-kinder-joy-stranger-things-eleven-1255845372",
          "reserved": true,
          "verdict": "skip",
          "reason": "precio < 3€ (truco SEO)"
        },
        {
          "title": "Funko Pop Dragonite Pokémon",
          "price": 10,
          "city": "Fuengirola",
          "url": "https://es.wallapop.com/item/funko-pop-dragonite-pokemon-1255844604",
          "reserved": false,
          "profile": "funko",
          "verdict": "skip",
          "reason": "funko problema: amarillo"
        },
        {
          "title": "Funko Pop! The Last Ronin Yi #58",
          "price": 10,
          "city": "Córdoba",
          "url": "https://es.wallapop.com/item/funko-pop-the-last-ronin-yi-58-1255844368",
          "reserved": false,
          "profile": "funko",
          "query_ebay": "Funko pop! the last ronin #58",
          "verdict": "skip",
          "reason": "0 reservados de 'Funko pop! the last ronin #58' (sin evidencia de demanda)"
        },
        {
          "title": "Funko Pop Cyborg Superman Comic Cover",
          "price": 15,
          "city": "Córdoba",
          "url": "https://es.wallapop.com/item/funko-pop-cyborg-superman-comic-cover-1255843972",
          "reserved": false,
          "profile": "funko",
          "query_ebay": "Funko cyborg superman comic cover",
          "verdict": "skip",
          "reason": "0 reservados de 'Funko cyborg superman comic cover' (sin evidencia de demanda)"
        },
        {
          "title": "Funko Pop LOTR Aragorn & Arwen 2 Pack",
          "price": 180,
          "city": "Burriana",
          "url": "https://es.wallapop.com/item/funko-pop-lotr-aragorn-arwen-2-pack-1255843848",
          "reserved": false,
          "profile": "funko",
          "query_ebay": "Funko lotr aragorn arwen pack",
          "verdict": "skip",
          "reason": "0 reservados de 'Funko lotr aragorn arwen pack' (sin evidencia de demanda)"
        },
        {
          "title": "Funko Pop Stranger Things",
          "price": 2,
          "city": "Fuengirola",
          "url": "https://es.wallapop.com/item/funko-pop-stranger-things-1255842772",
          "reserved": false,
          "verdict": "skip",
          "reason": "precio < 3€ (truco SEO)"
        },
        {
          "title": "Funko Pop! Eleven Stranger Things",
          "price": 2,
          "city": "Fuengirola",
          "url": "https://es.wallapop.com/item/funko-pop-eleven-stranger-things-1255842551",
          "reserved": false,
          "verdict": "skip",
          "reason": "precio < 3€ (truco SEO)"
        },
        {
          "title": "Lego Minifigure Serie 14 - Niña Tigre",
          "price": 7,
          "city": "Alghero",
          "url": "https://es.wallapop.com/item/lego-minifigure-serie-14-tiger-girl-1255846800",
          "reserved": false,
          "profile": "generic",
          "verdict": "skip",
          "reason": "ticket bajo (<10€), envío mata margen"
        },
        {
          "title": "Expositores Lego Star Wars Battle Packs",
          "price": 4,
          "city": "Ajalvir",
          "url": "https://es.wallapop.com/item/expositores-lego-star-wars-battle-packs-1255846360",
          "reserved": false,
          "profile": "generic",
          "verdict": "skip",
          "reason": "ticket bajo (<10€), envío mata margen"
        },
        {
          "title": "LEGO Super Mario 71420 Rambi el Elefante",
          "price": 17,
          "city": "Sant'Angelo in Salute",
          "url": "https://es.wallapop.com/item/lego-super-mario-71420-rambi-l-elefante-1255845737",
          "reserved": false,
          "profile": "generic",
          "query_ebay": "lego super mario rambi elefante",
          "verdict": "skip",
          "reason": "0 reservados de 'lego super mario rambi elefante' (sin evidencia de demanda)"
        },
        {
          "title": "Paquete de Potenciadores LEGO 71370 Super Mario",
          "price": 20,
          "city": "Sant'Angelo in Salute",
          "url": "https://es.wallapop.com/item/lego-71370-super-mario-power-up-pack-1255845251",
          "reserved": false,
          "profile": "generic",
          "query_ebay": "paquete potenciadores lego super mario",
          "verdict": "skip",
          "reason": "0 reservados de 'paquete potenciadores lego super mario' (sin evidencia de demanda)"
        },
        {
          "title": "LEGO STAR WARS 75362 SABINE WREN",
          "price": 12,
          "city": "Benade",
          "url": "https://es.wallapop.com/item/lego-star-wars-75362-sabine-wren-1255844027",
          "reserved": false,
          "profile": "generic",
          "query_ebay": "lego star wars sabine wren",
          "verdict": "skip",
          "reason": "0 reservados de 'lego star wars sabine wren' (sin evidencia de demanda)"
        },
        {
          "title": "LEGO STAR WARS 75316 BO-KATAN KRYZE",
          "price": 18,
          "city": "Benade",
          "url": "https://es.wallapop.com/item/lego-star-wars-75316-bo-katan-kryze-1255843124",
          "reserved": false,
          "profile": "generic",
          "query_ebay": "lego star wars bo-katan kryze",
          "verdict": "skip",
          "reason": "0 reservados de 'lego star wars bo-katan kryze' (sin evidencia de demanda)"
        },
        {
          "title": "Minifigura Thanos con Guantelete del Infinito",
          "price": 7,
          "city": "Barcelona",
          "url": "https://es.wallapop.com/item/minifigura-thanos-con-guantelete-del-infinito-1255842673",
          "reserved": false,
          "profile": "generic",
          "verdict": "skip",
          "reason": "ticket bajo (<10€), envío mata margen"
        },
        {
          "title": "Expositor para Lego Star Wars",
          "price": 5,
          "city": "Ajalvir",
          "url": "https://es.wallapop.com/item/expositor-para-lego-star-wars-1255842559",
          "reserved": false,
          "profile": "generic",
          "verdict": "skip",
          "reason": "ticket bajo (<10€), envío mata margen"
        },
        {
          "title": "2025-26 Megacracks Fichaje Rookie Etta Eyong",
          "price": 9,
          "city": "Madrid",
          "url": "https://es.wallapop.com/item/2025-26-megacracks-fichaje-rookie-etta-eyong-1255846825",
          "reserved": false,
          "profile": "generic",
          "verdict": "skip",
          "reason": "ticket bajo (<10€), envío mata margen"
        },
        {
          "title": "Vendo Momentum Joan García",
          "price": 9.5,
          "city": "Móstoles",
          "url": "https://es.wallapop.com/item/vendo-momentum-joan-garcia-1255846680",
          "reserved": false,
          "profile": "generic",
          "verdict": "skip",
          "reason": "ticket bajo (<10€), envío mata margen"
        },
        {
          "title": "Cambios y Ventas Panini Adrenalyn XL 2025-26",
          "price": 1,
          "city": "Cantalejo",
          "url": "https://es.wallapop.com/item/cambios-y-ventas-panini-adrenalyn-xl-2025-26-1255846225",
          "reserved": false,
          "verdict": "skip",
          "reason": "precio < 3€ (truco SEO)"
        },
        {
          "title": "2024-25 Liga Este Real Madrid Fichaje Mbappé",
          "price": 10,
          "city": "Madrid",
          "url": "https://es.wallapop.com/item/2024-25-liga-este-real-madrid-fichaje-mbappe-1255845850",
          "reserved": false,
          "profile": "generic",
          "query_ebay": "2024-25 liga este real madrid",
          "verdict": "skip",
          "reason": "0 reservados de '2024-25 liga este real madrid' (sin evidencia de demanda)"
        },
        {
          "title": "Cromos de Lamine Yamal Panini FC Barcelona",
          "price": 175,
          "city": "El Barco de Ávila",
          "url": "https://es.wallapop.com/item/cromo-lamine-yamal-panini-fc-barcelona-1255845358",
          "reserved": false,
          "profile": "generic",
          "query_ebay": "cromos lamine yamal panini barcelona",
          "verdict": "skip",
          "reason": "175€ vs mín reservado 5€ (margen <30%, no es ganga clara)"
        },
        {
          "title": "Panini Instant Lamine Yamal Hat Trick Numerado",
          "price": 12,
          "city": "Madrid",
          "url": "https://es.wallapop.com/item/panini-instant-lamine-yamal-hat-trick-numerado-1255844735",
          "reserved": false,
          "profile": "generic",
          "query_ebay": "panini instant lamine yamal hat",
          "verdict": "skip",
          "reason": "12€ vs mín reservado 5€ (margen <30%, no es ganga clara)"
        },
        {
          "title": "Surfing Pikachu EVO 111/108 EN",
          "price": 10,
          "city": "Sant Celoni",
          "url": "https://es.wallapop.com/item/surfing-pikachu-evo-111-108-en-1255846775",
          "reserved": false,
          "profile": "generic",
          "query_ebay": "surfing pikachu evo 111/108",
          "verdict": "skip",
          "reason": "0 reservados de 'surfing pikachu evo 111/108' (sin evidencia de demanda)"
        },
        {
          "title": "Pikachu EX SSP 219/191 ES",
          "price": 29,
          "city": "Sant Celoni",
          "url": "https://es.wallapop.com/item/pikachu-ex-ssp-219-191-es-1255845551",
          "reserved": false,
          "profile": "generic",
          "query_ebay": "pikachu ssp 219/191",
          "verdict": "skip",
          "reason": "0 reservados de 'pikachu ssp 219/191' (sin evidencia de demanda)"
        },
        {
          "title": "Alakazam EX 125/124 FCO ES",
          "price": 75,
          "city": "Sant Celoni",
          "url": "https://es.wallapop.com/item/alakazam-ex-125-124-fco-es-1255844403",
          "reserved": false,
          "profile": "generic",
          "query_ebay": "alakazam 125/124 fco",
          "verdict": "skip",
          "reason": "0 reservados de 'alakazam 125/124 fco' (sin evidencia de demanda)"
        },
        {
          "title": "Caja Coleccionista Secretos de Strixhaven MTG",
          "price": 320,
          "city": "Vilanova i la Geltrú",
          "url": "https://es.wallapop.com/item/caja-coleccionista-secretos-de-strixhaven-mtg-1255844179",
          "reserved": false,
          "profile": "generic",
          "query_ebay": "coleccionista secretos strixhaven mtg",
          "verdict": "skip",
          "reason": "0 reservados de 'coleccionista secretos strixhaven mtg' (sin evidencia de demanda)"
        },
        {
          "title": "Magic Strixhaven Caja Sobres",
          "price": 130,
          "city": "Vilanova i la Geltrú",
          "url": "https://es.wallapop.com/item/magic-strixhaven-caja-sobres-1255843759",
          "reserved": false,
          "profile": "generic",
          "query_ebay": "magic strixhaven sobres",
          "verdict": "skip",
          "reason": "130€ vs mín reservado 120€ (margen <30%, no es ganga clara)"
        },
        {
          "title": "Zoroark EX de N 189/159 Carta Pokémon",
          "price": 25,
          "city": "Panorama",
          "url": "https://es.wallapop.com/item/zoroark-ex-de-n-189-159-carta-pokemon-1255848491",
          "reserved": false,
          "profile": "generic",
          "query_ebay": "zoroark 189/159 carta pokemon",
          "verdict": "skip",
          "reason": "0 reservados de 'zoroark 189/159 carta pokemon' (sin evidencia de demanda)"
        },
        {
          "title": "Carta Pokémon Diglett 50/144 Base Set",
          "price": 10,
          "city": "Alghero",
          "url": "https://es.wallapop.com/item/carta-pokemon-diglett-50-144-base-set-1255848057",
          "reserved": false,
          "profile": "generic",
          "query_ebay": "carta pokemon diglett 50/144 base",
          "verdict": "skip",
          "reason": "0 reservados de 'carta pokemon diglett 50/144 base' (sin evidencia de demanda)"
        },
        {
          "title": "Carta Pokémon Heliolisk ASCES 229/217",
          "price": 3,
          "city": "Benabarre",
          "url": "https://es.wallapop.com/item/carta-pokemon-heliolisk-asces-229-217-1255847994",
          "reserved": false,
          "profile": "generic",
          "verdict": "skip",
          "reason": "ticket bajo (<10€), envío mata margen"
        },
        {
          "title": "Álbum Cartas Pokémon 380 Cartas",
          "price": 13,
          "city": "Vila-Seca",
          "url": "https://es.wallapop.com/item/album-cartas-pokemon-380-cartas-1255844637",
          "reserved": false,
          "profile": "generic",
          "query_ebay": "album cartas pokemon cartas",
          "verdict": "skip",
          "reason": "activos saturados (mín activo 6€ vs mín reservado 40€)"
        },
        {
          "title": "Lote de 200 cartas Pokémon Energías y códigos",
          "price": 5,
          "city": "Grumello del Monte",
          "url": "https://es.wallapop.com/item/lotto-200-carte-pokemon-energie-e-codici-1255844578",
          "reserved": false,
          "profile": "generic",
          "verdict": "skip",
          "reason": "ticket bajo (<10€), envío mata margen"
        },
        {
          "title": "Mew EX 232/091 Carta Pokémon",
          "price": 540,
          "city": "Algeciras",
          "url": "https://es.wallapop.com/item/mew-ex-232-091-carta-pokemon-1255844040",
          "reserved": false,
          "profile": "generic",
          "query_ebay": "mew 232/091 carta pokemon",
          "verdict": "skip",
          "reason": "0 reservados de 'mew 232/091 carta pokemon' (sin evidencia de demanda)"
        },
        {
          "title": "Carta Pokémon Arceus V",
          "price": 34,
          "city": "Majadahonda",
          "url": "https://es.wallapop.com/item/carta-pokemon-arceus-v-1255843370",
          "reserved": false,
          "profile": "generic",
          "query_ebay": "carta pokemon arceus",
          "verdict": "skip",
          "reason": "activos saturados (mín activo 9€ vs mín reservado 460€)"
        },
        {
          "title": "Carta Pokémon Aggron 100 HP",
          "price": 2.5,
          "city": "Barcelona",
          "url": "https://es.wallapop.com/item/carta-pokemon-aggron-100-hp-1255843117",
          "reserved": false,
          "verdict": "skip",
          "reason": "precio < 3€ (truco SEO)"
        },
        {
          "title": "Carta Pokémon Aurorus Fase 2 170 PS",
          "price": 6,
          "city": "Monforte de Lemos",
          "url": "https://es.wallapop.com/item/carta-pokemon-aurorus-fase-2-170-ps-1255842654",
          "reserved": false,
          "profile": "generic",
          "verdict": "skip",
          "reason": "ticket bajo (<10€), envío mata margen"
        },
        {
          "title": "Playmobil cura y monja con cáliz y biblia",
          "price": 10,
          "city": "Málaga",
          "url": "https://es.wallapop.com/item/playmobil-cura-y-monja-con-caliz-y-biblia-1255844690",
          "reserved": false,
          "profile": "generic",
          "query_ebay": "playmobil cura monja con caliz",
          "verdict": "skip",
          "reason": "0 reservados de 'playmobil cura monja con caliz' (sin evidencia de demanda)"
        }
      ],
      "signals": 0
    },
    "Tecnología y electrónica": {
      "total_items": 254,
      "new_items": 124,
      "items": [
        {
          "title": "Nintendo Switch + Ring Fit",
          "price": 200,
          "city": "Lugones",
          "url": "https://es.wallapop.com/item/nintendo-switch---ring-fit-1255848439",
          "reserved": false,
          "profile": "videojuego_switch",
          "verdict": "skip",
          "reason": "pack (pack_consola_juegos): comparación eBay imprecisa, skip conservador"
        },
        {
          "title": "Splatoon 2 Nintendo Switch precintado",
          "price": 20,
          "city": "La Puebla de Montalbán",
          "url": "https://es.wallapop.com/item/splatoon-2-nintendo-switch-precintado-1255848416",
          "reserved": false,
          "profile": "videojuego_switch",
          "query_ebay": "splatoon nintendo switch",
          "verdict": "skip",
          "reason": "20€ vs mín reservado 9€ (margen <30%, no es ganga clara)"
        },
        {
          "title": "Hammerwatch 2 - The Chronicles Edition Nintendo",
          "price": 15,
          "city": "Évora",
          "url": "https://es.wallapop.com/item/hammerwatch-2-the-chronicles-edition-nintendo-1255848314",
          "reserved": false,
          "profile": "videojuego_switch",
          "query_ebay": "hammerwatch the chronicles edition nintendo",
          "verdict": "skip",
          "reason": "0 reservados de 'hammerwatch the chronicles edition nintendo' (sin evidencia de demanda)"
        },
        {
          "title": "Pack 4 Juegos Nintendo Switch: Mario, Spyro, Grinc",
          "price": 0,
          "city": "Granada",
          "url": "https://es.wallapop.com/item/pack-4-juegos-nintendo-switch-mario-spyro-grinc-1255847600",
          "reserved": false,
          "verdict": "skip",
          "reason": "precio < 3€ (truco SEO)"
        },
        {
          "title": "Expositor juegos PS4/PS5/Switch",
          "price": 8.5,
          "city": "Jaén",
          "url": "https://es.wallapop.com/item/expositor-juegos-ps4-ps5-switch-1255847388",
          "reserved": false,
          "profile": "videojuego_switch",
          "verdict": "skip",
          "reason": "precio ambiguo: field=8.5€ pero desc menciona 90€"
        },
        {
          "title": "Nintendo Switch Azul y Rojo",
          "price": 160,
          "city": "Fuentes de Andalucía",
          "url": "https://es.wallapop.com/item/nintendo-switch-azul-y-rojo-1255846972",
          "reserved": false,
          "profile": "videojuego_switch",
          "query_ebay": "nintendo switch azul rojo",
          "verdict": "skip",
          "reason": "160€ vs mín reservado 35€ (margen <30%, no es ganga clara)"
        },
        {
          "title": "Pokemon Perla Reluciente Nintendo Switch",
          "price": 36.5,
          "city": "Vidreres",
          "url": "https://es.wallapop.com/item/pokemon-perla-reluciente-nintendo-switch-1255846743",
          "reserved": false,
          "profile": "videojuego_switch",
          "query_ebay": "pokemon perla reluciente nintendo switch",
          "verdict": "skip",
          "reason": "36.5€ vs mín reservado 25€ (margen <30%, no es ganga clara)"
        },
        {
          "title": "Luigi's Mansion 3 Nintendo Switch",
          "price": 27,
          "city": "Granada",
          "url": "https://es.wallapop.com/item/luigi-s-mansion-3-nintendo-switch-1255846703",
          "reserved": false,
          "profile": "videojuego_switch",
          "query_ebay": "luigi's mansion nintendo switch",
          "verdict": "skip",
          "reason": "27€ vs mín reservado 25€ (margen <30%, no es ganga clara)"
        },
        {
          "title": "Pokémon Púrpura Nintendo Switch",
          "price": 32,
          "city": "Cerdanyola del Vallès",
          "url": "https://es.wallapop.com/item/pokemon-purpura-nintendo-switch-1255846590",
          "reserved": false,
          "profile": "videojuego_switch",
          "query_ebay": "pokemon purpura nintendo switch",
          "verdict": "skip",
          "reason": "activos saturados (mín activo 10€ vs mín reservado 50€)"
        },
        {
          "title": "Dragon Ball Z Kakarot + A New Power Awakens Set",
          "price": 20,
          "city": "Cerdanyola del Vallès",
          "url": "https://es.wallapop.com/item/dragon-ball-z-kakarot---a-new-power-awakens-set-1255846024",
          "reserved": false,
          "profile": "videojuego_switch",
          "query_ebay": "dragon ball kakarot new power Nintendo Switch",
          "verdict": "skip",
          "reason": "0 reservados de 'dragon ball kakarot new power Nintendo Switch' (sin evidencia de demanda)"
        },
        {
          "title": "Nintendo Switch",
          "price": 140,
          "city": "Sant Cugat del Vallès",
          "url": "https://es.wallapop.com/item/nintendo-switch-1255845930",
          "reserved": false,
          "profile": "videojuego_switch",
          "query_ebay": "nintendo switch",
          "verdict": "skip",
          "reason": "0 reservados de 'nintendo switch' (sin evidencia de demanda)"
        },
        {
          "title": "Juego The Grinch Christmas Adventures Switch",
          "price": 25,
          "city": "Granada",
          "url": "https://es.wallapop.com/item/juego-the-grinch-christmas-adventures-switch-1255845840",
          "reserved": false,
          "profile": "videojuego_switch",
          "query_ebay": "the grinch christmas adventures switch",
          "verdict": "skip",
          "reason": "0 reservados de 'the grinch christmas adventures switch' (sin evidencia de demanda)"
        },
        {
          "title": "Mando Pro Nintendo Switch",
          "price": 30,
          "city": "Madrid",
          "url": "https://es.wallapop.com/item/mando-pro-nintendo-switch-1255845742",
          "reserved": false,
          "profile": "videojuego_switch",
          "query_ebay": "mando pro nintendo switch",
          "verdict": "skip",
          "reason": "competencia alta: 9 vendedores activos del mismo producto"
        },
        {
          "title": "Animal Crossing New Horizons Switch",
          "price": 35,
          "city": "Badajoz",
          "url": "https://es.wallapop.com/item/animal-crossing-new-horizons-switch-1255845524",
          "reserved": false,
          "profile": "videojuego_switch",
          "query_ebay": "animal crossing new horizons switch",
          "verdict": "skip",
          "reason": "35€ vs mín reservado 20€ (margen <30%, no es ganga clara)"
        },
        {
          "title": "Nintendo Switch HAC-01 Caja Completa",
          "price": 149.9,
          "city": "Montesilvano",
          "url": "https://es.wallapop.com/item/nintendo-switch-hac-01-completa-boxata-1255845438",
          "reserved": false,
          "profile": "videojuego_switch",
          "query_ebay": "nintendo switch hac-01 completa",
          "verdict": "skip",
          "reason": "0 reservados de 'nintendo switch hac-01 completa' (sin evidencia de demanda)"
        },
        {
          "title": "Spyro Reignited Trilogy Nintendo Switch",
          "price": 20,
          "city": "Granada",
          "url": "https://es.wallapop.com/item/spyro-reignited-trilogy-nintendo-switch-1255845036",
          "reserved": false,
          "profile": "videojuego_switch",
          "query_ebay": "spyro reignited trilogy nintendo switch",
          "verdict": "skip",
          "reason": "0 reservados de 'spyro reignited trilogy nintendo switch' (sin evidencia de demanda)"
        },
        {
          "title": "Nintendo Switch Lite Zacian & Zamazenta",
          "price": 170,
          "city": "Montesilvano",
          "url": "https://es.wallapop.com/item/nintendo-switch-lite-zacian-zamazenta-1255844722",
          "reserved": false,
          "profile": "videojuego_switch",
          "verdict": "skip",
          "reason": "juego >80€ difícil arbitrar"
        },
        {
          "title": "Póster promocional de Pokémon Escarlata y Violeta con pegatinas",
          "price": 15,
          "city": "Alghero",
          "url": "https://es.wallapop.com/item/poster-promo-pokemon-scarlatto-e-violetto-adesivi-1255844672",
          "reserved": false,
          "profile": "videojuego_switch",
          "query_ebay": "poster promocional pokemon escarlata violeta Nintendo Switch",
          "verdict": "skip",
          "reason": "0 reservados de 'poster promocional pokemon escarlata violeta Nintendo Switch' (sin evidencia de demanda)"
        },
        {
          "title": "Super Mario Bros Wonder Nintendo Switch",
          "price": 35,
          "city": "Badajoz",
          "url": "https://es.wallapop.com/item/super-mario-bros-wonder-nintendo-switch-1255844653",
          "reserved": false,
          "profile": "videojuego_switch",
          "query_ebay": "super mario bros wonder nintendo",
          "verdict": "skip",
          "reason": "35€ vs mín reservado 30€ (margen <30%, no es ganga clara)"
        },
        {
          "title": "Nintendo Switch Negra",
          "price": 350,
          "city": "Valencia",
          "url": "https://es.wallapop.com/item/nintendo-switch-negra-1255844628",
          "reserved": false,
          "profile": "videojuego_switch",
          "query_ebay": "nintendo switch negra",
          "verdict": "skip",
          "reason": "350€ vs mín reservado 20€ (margen <30%, no es ganga clara)"
        },
        {
          "title": "Pokémon Zafiro GBA Español Nintendo",
          "price": 35,
          "city": "Sant Vicent del Raspeig",
          "url": "https://es.wallapop.com/item/pokemon-zafiro-gba-espanol-nintendo-1255844593",
          "reserved": false,
          "profile": "videojuego_switch",
          "query_ebay": "pokemon zafiro gba espanol nintendo",
          "verdict": "skip",
          "reason": "0 reservados de 'pokemon zafiro gba espanol nintendo' (sin evidencia de demanda)"
        },
        {
          "title": "Juego Nintendo Switch Spongebob Patrick Star",
          "price": 20,
          "city": "Granada",
          "url": "https://es.wallapop.com/item/juego-nintendo-switch-spongebob-patrick-star-1255844228",
          "reserved": false,
          "profile": "videojuego_switch",
          "query_ebay": "nintendo switch spongebob patrick star",
          "verdict": "skip",
          "reason": "0 reservados de 'nintendo switch spongebob patrick star' (sin evidencia de demanda)"
        },
        {
          "title": "Consola Super Nintendo SNES PAL",
          "price": 90,
          "city": "Sant Vicent del Raspeig",
          "url": "https://es.wallapop.com/item/consola-super-nintendo-snes-pal-1255844122",
          "reserved": false,
          "profile": "videojuego_switch",
          "query_ebay": "super nintendo snes pal",
          "verdict": "skip",
          "reason": "90€ vs mín reservado 19.99€ (margen <30%, no es ganga clara)"
        },
        {
          "title": "Precintado - Mighty Morphin Power Rangers",
          "price": 24.5,
          "city": "Vigo",
          "url": "https://es.wallapop.com/item/precintado-mighty-morphin-power-rangers-1255843891",
          "reserved": false,
          "profile": "videojuego_switch",
          "query_ebay": "mighty morphin power rangers Nintendo Switch",
          "verdict": "skip",
          "reason": "0 reservados de 'mighty morphin power rangers Nintendo Switch' (sin evidencia de demanda)"
        },
        {
          "title": "Lector Tarjetas juego para Nintendo Switch",
          "price": 15,
          "city": "Altsasu/Alsasua",
          "url": "https://es.wallapop.com/item/lector-tarjetas-juego-para-nintendo-switch-1255843872",
          "reserved": false,
          "profile": "videojuego_switch",
          "query_ebay": "lector tarjetas nintendo switch",
          "verdict": "skip",
          "reason": "0 reservados de 'lector tarjetas nintendo switch' (sin evidencia de demanda)"
        },
        {
          "title": "Mr. Bean - PlayStation 2 (PAL España) ps2",
          "price": 15,
          "city": "Sant Vicent del Raspeig",
          "url": "https://es.wallapop.com/item/mr-bean-playstation-2-pal-espana-ps2-1255843444",
          "reserved": false,
          "profile": "videojuego_switch",
          "query_ebay": "mr. bean playstation (pal espana) Nintendo Switch",
          "verdict": "skip",
          "reason": "0 reservados de 'mr. bean playstation (pal espana) Nintendo Switch' (sin evidencia de demanda)"
        },
        {
          "title": "Joy-Con para Nintendo Switch",
          "price": 14.99,
          "city": "Almazora/Almassora",
          "url": "https://es.wallapop.com/item/joy-con-para-nintendo-switch-1255843405",
          "reserved": false,
          "profile": "videojuego_switch",
          "verdict": "skip",
          "reason": "precio fuera de rango razonable"
        },
        {
          "title": "Minecraft Nintendo Switch",
          "price": 20,
          "city": "Andratx",
          "url": "https://es.wallapop.com/item/minecraft-nintendo-switch-1255843382",
          "reserved": false,
          "profile": "videojuego_switch",
          "query_ebay": "minecraft nintendo switch",
          "verdict": "skip",
          "reason": "20€ vs mín reservado 15€ (margen <30%, no es ganga clara)"
        },
        {
          "title": "Nintendo Switch + Accesorios + Funda",
          "price": 175,
          "city": "Elx/Elche",
          "url": "https://es.wallapop.com/item/nintendo-switch---accesorios---funda-1255843372",
          "reserved": false,
          "profile": "videojuego_switch",
          "query_ebay": "nintendo switch accesorios funda",
          "verdict": "skip",
          "reason": "175€ vs mín reservado 160€ (margen <30%, no es ganga clara)"
        },
        {
          "title": "Joy-Con Nintendo Switch Mario y Luigi nuevos",
          "price": 14.99,
          "city": "Almazora/Almassora",
          "url": "https://es.wallapop.com/item/joy-con-nintendo-switch-mario-y-luigi-nuevos-1255843210",
          "reserved": false,
          "profile": "videojuego_switch",
          "query_ebay": "joy-con nintendo switch mario luigi",
          "verdict": "skip",
          "reason": "0 reservados de 'joy-con nintendo switch mario luigi' (sin evidencia de demanda)"
        },
        {
          "title": "Mario + Rabbids Kingdom Battle Switch",
          "price": 15,
          "city": "Granada",
          "url": "https://es.wallapop.com/item/mario---rabbids-kingdom-battle-switch-1255842986",
          "reserved": false,
          "profile": "videojuego_switch",
          "query_ebay": "mario rabbids kingdom battle switch",
          "verdict": "skip",
          "reason": "0 reservados de 'mario rabbids kingdom battle switch' (sin evidencia de demanda)"
        },
        {
          "title": "Joy-Con Nintendo Switch Nuevos",
          "price": 14.99,
          "city": "Almazora/Almassora",
          "url": "https://es.wallapop.com/item/joy-con-nintendo-switch-nuevos-1255842971",
          "reserved": false,
          "profile": "videojuego_switch",
          "verdict": "skip",
          "reason": "precio fuera de rango razonable"
        },
        {
          "title": "🆕 -SIN ABRIR-  Neva Nintendo switch PAL 🇪🇦",
          "price": 26.95,
          "city": "Leganés",
          "url": "https://es.wallapop.com/item/sin-abrir-neva-nintendo-switch-pal-1255842947",
          "reserved": false,
          "profile": "videojuego_switch",
          "query_ebay": "-sin abrir- neva nintendo switch",
          "verdict": "skip",
          "reason": "0 reservados de '-sin abrir- neva nintendo switch' (sin evidencia de demanda)"
        },
        {
          "title": "Precintado - Unicorn Overlord Nintendo Switch",
          "price": 29.95,
          "city": "Vigo",
          "url": "https://es.wallapop.com/item/precintado-unicorn-overlord-nintendo-switch-1255842854",
          "reserved": false,
          "profile": "videojuego_switch",
          "query_ebay": "unicorn overlord nintendo switch",
          "verdict": "skip",
          "reason": "29.95€ vs mín reservado 29€ (margen <30%, no es ganga clara)"
        },
        {
          "title": "Nintendo Switch 2 Gris/Rojo",
          "price": 350,
          "city": "Cerdanyola del Vallès",
          "url": "https://es.wallapop.com/item/nintendo-switch-2-gris-rojo-1255842678",
          "reserved": false,
          "profile": "videojuego_switch",
          "query_ebay": "nintendo switch gris/rojo",
          "verdict": "skip",
          "reason": "350€ vs mín reservado 110€ (margen <30%, no es ganga clara)"
        },
        {
          "title": "Dying Light Platinum Edition Nintendo Switch",
          "price": 49.99,
          "city": "Almazora/Almassora",
          "url": "https://es.wallapop.com/item/dying-light-platinum-edition-nintendo-switch-1255842508",
          "reserved": false,
          "profile": "videojuego_switch",
          "query_ebay": "dying light platinum edition nintendo",
          "verdict": "skip",
          "reason": "0 reservados de 'dying light platinum edition nintendo' (sin evidencia de demanda)"
        },
        {
          "title": "Call of Duty Black Ops 6 PS5",
          "price": 15,
          "city": "Málaga",
          "url": "https://es.wallapop.com/item/call-of-duty-black-ops-6-ps5-1255848011",
          "reserved": false,
          "profile": "generic",
          "query_ebay": "call duty black ops ps5",
          "verdict": "skip",
          "reason": "15€ vs mín reservado 16€ (margen <30%, no es ganga clara)"
        },
        {
          "title": "Cambio PS5 por Xbox Series X",
          "price": 400,
          "city": "Sant Gregori",
          "url": "https://es.wallapop.com/item/cambio-ps5-por-xbox-series-x-1255847880",
          "reserved": false,
          "profile": "generic",
          "query_ebay": "cambio ps5 por xbox series",
          "verdict": "skip",
          "reason": "0 reservados de 'cambio ps5 por xbox series' (sin evidencia de demanda)"
        },
        {
          "title": "NBA 2K 22 PS5",
          "price": 9.99,
          "city": "Sevilla",
          "url": "https://es.wallapop.com/item/nba-2k-22-ps5-1255847868",
          "reserved": false,
          "profile": "generic",
          "verdict": "skip",
          "reason": "ticket bajo (<10€), envío mata margen"
        },
        {
          "title": "Mando PS5 Antidrift Dragon Ball Magnético TMR",
          "price": 90,
          "city": "Barcelona",
          "url": "https://es.wallapop.com/item/mando-ps5-antidrift-dragon-ball-magnetico-tmr-1255847827",
          "reserved": false,
          "profile": "generic",
          "query_ebay": "mando ps5 antidrift dragon ball",
          "verdict": "skip",
          "reason": "0 reservados de 'mando ps5 antidrift dragon ball' (sin evidencia de demanda)"
        },
        {
          "title": "Call of Duty Modern Warfare II PS5",
          "price": 18,
          "city": "Málaga",
          "url": "https://es.wallapop.com/item/call-of-duty-modern-warfare-ii-ps5-1255847784",
          "reserved": false,
          "profile": "generic",
          "query_ebay": "call duty modern warfare ps5",
          "verdict": "skip",
          "reason": "competencia alta: 9 vendedores activos del mismo producto"
        },
        {
          "title": "Assassin's Creed Shadows PS5",
          "price": 25,
          "city": "Irun",
          "url": "https://es.wallapop.com/item/assassin-s-creed-shadows-ps5-1255847551",
          "reserved": false,
          "profile": "generic",
          "query_ebay": "assassin's creed shadows ps5",
          "verdict": "skip",
          "reason": "0 reservados de 'assassin's creed shadows ps5' (sin evidencia de demanda)"
        },
        {
          "title": "FC 25 PS5 (EA Sports)",
          "price": 30,
          "city": "La Puebla de Montalbán",
          "url": "https://es.wallapop.com/item/fc-25-ps5-ea-sports-1255847340",
          "reserved": false,
          "profile": "generic",
          "query_ebay": "ps5 (ea sports)",
          "verdict": "skip",
          "reason": "30€ vs mín reservado 25€ (margen <30%, no es ganga clara)"
        },
        {
          "title": "Pack 2 Mandos PS5 Nuevos",
          "price": 84,
          "city": "Madrid",
          "url": "https://es.wallapop.com/item/pack-2-mandos-ps5-nuevos-1255847227",
          "reserved": false,
          "profile": "generic",
          "query_ebay": "pack mandos ps5 nuevos",
          "verdict": "skip",
          "reason": "0 reservados de 'pack mandos ps5 nuevos' (sin evidencia de demanda)"
        },
        {
          "title": "Auriculares Gaming Estéreo con Micrófono",
          "price": 10,
          "city": "León",
          "url": "https://es.wallapop.com/item/auriculares-gaming-estereo-con-microfono-1255847105",
          "reserved": false,
          "profile": "generic",
          "query_ebay": "auriculares gaming estereo con microfono",
          "verdict": "skip",
          "reason": "0 reservados de 'auriculares gaming estereo con microfono' (sin evidencia de demanda)"
        },
        {
          "title": "Sonos Play 5 Gen 2",
          "price": 300,
          "city": "Alhaurín de la Torre",
          "url": "https://es.wallapop.com/item/sonos-play-5-gen-2-1255847057",
          "reserved": false,
          "profile": "generic",
          "query_ebay": "sonos play gen",
          "verdict": "skip",
          "reason": "0 reservados de 'sonos play gen' (sin evidencia de demanda)"
        },
        {
          "title": "Metal Gear Solid Delta: Snake Eater PS5",
          "price": 36,
          "city": "A Fraga",
          "url": "https://es.wallapop.com/item/metal-gear-solid-delta-snake-eater-ps5-1255846625",
          "reserved": false,
          "profile": "generic",
          "query_ebay": "metal gear solid delta: snake",
          "verdict": "skip",
          "reason": "36€ vs mín reservado 30€ (margen <30%, no es ganga clara)"
        },
        {
          "title": "Days Gone PS4",
          "price": 30,
          "city": "Cuarte de Huerva",
          "url": "https://es.wallapop.com/item/days-gone-ps4-1255846485",
          "reserved": false,
          "profile": "generic",
          "query_ebay": "days gone ps4",
          "verdict": "skip",
          "reason": "0 reservados de 'days gone ps4' (sin evidencia de demanda)"
        },
        {
          "title": "PS5 Let's Sing 2024 + Micrófono",
          "price": 50,
          "city": "La Puebla de Montalbán",
          "url": "https://es.wallapop.com/item/ps5-let-s-sing-2024---microfono-1255846274",
          "reserved": false,
          "profile": "generic",
          "query_ebay": "ps5 let's sing microfono",
          "verdict": "skip",
          "reason": "0 reservados de 'ps5 let's sing microfono' (sin evidencia de demanda)"
        },
        {
          "title": "Soul Reaver 1 & 2 Deluxe Edition PS5 NUEVO",
          "price": 45,
          "city": "Barcelona",
          "url": "https://es.wallapop.com/item/soul-reaver-1-2-deluxe-edition-ps5-nuevo-1255845520",
          "reserved": false,
          "profile": "generic",
          "query_ebay": "soul reaver deluxe edition ps5",
          "verdict": "skip",
          "reason": "0 reservados de 'soul reaver deluxe edition ps5' (sin evidencia de demanda)"
        },
        {
          "title": "Ghost of Yotei PS5",
          "price": 40,
          "city": "Zaragoza",
          "url": "https://es.wallapop.com/item/ghost-of-yotei-ps5-juego-de-accion-1255845092",
          "reserved": false,
          "profile": "generic",
          "query_ebay": "ghost yotei ps5",
          "verdict": "skip",
          "reason": "40€ vs mín reservado 27€ (margen <30%, no es ganga clara)"
        },
        {
          "title": "Mando PS5 Nuevo Sin Estrenar",
          "price": 50,
          "city": "Madrid",
          "url": "https://es.wallapop.com/item/mando-ps5-nuevo-sin-estrenar-1255844867",
          "reserved": false,
          "profile": "generic",
          "query_ebay": "mando ps5 sin estrenar",
          "verdict": "skip",
          "reason": "0 reservados de 'mando ps5 sin estrenar' (sin evidencia de demanda)"
        },
        {
          "title": "God of War Ragnarök PS5 precintado",
          "price": 25,
          "city": "La Puebla de Montalbán",
          "url": "https://es.wallapop.com/item/god-of-war-ragnarok-ps5-precintado-1255844788",
          "reserved": false,
          "profile": "generic",
          "query_ebay": "god war ragnarok ps5 precintado",
          "verdict": "skip",
          "reason": "0 reservados de 'god war ragnarok ps5 precintado' (sin evidencia de demanda)"
        },
        {
          "title": "Crimson Desert Deluxe Edition PS5",
          "price": 100,
          "city": "Móstoles",
          "url": "https://es.wallapop.com/item/crimson-desert-deluxe-edition-ps5-1255843985",
          "reserved": false,
          "profile": "generic",
          "query_ebay": "crimson desert deluxe edition ps5",
          "verdict": "skip",
          "reason": "0 reservados de 'crimson desert deluxe edition ps5' (sin evidencia de demanda)"
        },
        {
          "title": "Agarres Pulgar Mando PS4/PS5 Spider-Man",
          "price": 2,
          "city": "Collado Villalba",
          "url": "https://es.wallapop.com/item/agarres-pulgar-mando-ps4-ps5-spider-man-1255843535",
          "reserved": false,
          "verdict": "skip",
          "reason": "precio < 3€ (truco SEO)"
        },
        {
          "title": "Juego PS5 Marvel's Avengers Nuevo Sin Abrir 1por20",
          "price": 40,
          "city": "La Puebla de Montalbán",
          "url": "https://es.wallapop.com/item/juego-ps5-marvel-s-avengers-nuevo-sin-abrir-1por20-1255843410",
          "reserved": false,
          "profile": "generic",
          "query_ebay": "juego ps5 marvel's avengers sin",
          "verdict": "skip",
          "reason": "0 reservados de 'juego ps5 marvel's avengers sin' (sin evidencia de demanda)"
        },
        {
          "title": "Watch Dogs Legion PS5",
          "price": 15,
          "city": "Madrid",
          "url": "https://es.wallapop.com/item/watch-dogs-legion-ps5-1255843227",
          "reserved": false,
          "profile": "generic",
          "query_ebay": "watch dogs legion ps5",
          "verdict": "skip",
          "reason": "0 reservados de 'watch dogs legion ps5' (sin evidencia de demanda)"
        },
        {
          "title": "Juego PS5 Astro Bot.",
          "price": 25,
          "city": "Sevilla",
          "url": "https://es.wallapop.com/item/juego-ps5-astro-bot-1255843226",
          "reserved": false,
          "profile": "generic",
          "query_ebay": "juego ps5 astro bot.",
          "ebay_count": 0,
          "ebay_price_estimate": 0,
          "margin_net": 8.4,
          "margin_pct": 34,
          "score": 35,
          "from_cache": false,
          "verdict": "skip",
          "reason": "score bajo (net=8.4€, pct=34%, score=35)"
        },
        {
          "title": "Altavoces Samsung",
          "price": 20,
          "city": "Pamplona/Iruña",
          "url": "https://es.wallapop.com/item/altavoces-samsung-1255842976",
          "reserved": false,
          "profile": "generic",
          "query_ebay": "altavoces samsung",
          "verdict": "skip",
          "reason": "0 reservados de 'altavoces samsung' (sin evidencia de demanda)"
        },
        {
          "title": "FC 24 PS5",
          "price": 20,
          "city": "La Puebla de Montalbán",
          "url": "https://es.wallapop.com/item/fc-24-ps5-1255842716",
          "reserved": false,
          "profile": "generic",
          "verdict": "skip",
          "reason": "título sin términos útiles"
        },
        {
          "title": "F1 25 PS5 EA Sports",
          "price": 30,
          "city": "Castalla",
          "url": "https://es.wallapop.com/item/f1-25-ps5-ea-sports-1255842553",
          "reserved": false,
          "profile": "generic",
          "query_ebay": "ps5 sports",
          "verdict": "skip",
          "reason": "30€ vs mín reservado 25€ (margen <30%, no es ganga clara)"
        },
        {
          "title": "Consola Sony PS4 Negra/Gris",
          "price": 60,
          "city": "Corro d'Avall",
          "url": "https://es.wallapop.com/item/consola-sony-ps4-negra-gris-1255848105",
          "reserved": false,
          "profile": "generic",
          "query_ebay": "consola sony ps4 negra/gris",
          "verdict": "skip",
          "reason": "0 reservados de 'consola sony ps4 negra/gris' (sin evidencia de demanda)"
        },
        {
          "title": "PS4 con 2 mandos, 2 cables y bolsa",
          "price": 100,
          "city": "Móstoles",
          "url": "https://es.wallapop.com/item/ps4-con-2-mandos-2-cables-y-bolsa-1255846672",
          "reserved": false,
          "profile": "generic",
          "query_ebay": "ps4 con mandos, cables bolsa",
          "verdict": "skip",
          "reason": "0 reservados de 'ps4 con mandos, cables bolsa' (sin evidencia de demanda)"
        },
        {
          "title": "Consola PS4 Slim 500GB",
          "price": 99,
          "city": "Granollers",
          "url": "https://es.wallapop.com/item/consola-ps4-slim-500gb-1255845743",
          "reserved": false,
          "profile": "generic",
          "query_ebay": "consola ps4 slim 500gb",
          "verdict": "skip",
          "reason": "99€ vs mín reservado 80€ (margen <30%, no es ganga clara)"
        },
        {
          "title": "Consola PS4 Slim 1TB Negra",
          "price": 129,
          "city": "Granollers",
          "url": "https://es.wallapop.com/item/consola-ps4-slim-1tb-negra-1255844929",
          "reserved": false,
          "profile": "generic",
          "query_ebay": "consola ps4 slim 1tb negra",
          "verdict": "skip",
          "reason": "0 reservados de 'consola ps4 slim 1tb negra' (sin evidencia de demanda)"
        },
        {
          "title": "COMO NUEVA XBOX SERIES S",
          "price": 200,
          "city": "Manresa",
          "url": "https://es.wallapop.com/item/como-nueva-xbox-series-s-1255844649",
          "reserved": false,
          "profile": "generic",
          "query_ebay": "como nueva xbox series",
          "verdict": "skip",
          "reason": "0 reservados de 'como nueva xbox series' (sin evidencia de demanda)"
        },
        {
          "title": "BIGBEN Auriculares Stereo Xbox Series X|S",
          "price": 9.99,
          "city": "Madrid",
          "url": "https://es.wallapop.com/item/bigben-auriculares-stereo-xbox-series-x-s-1255842474",
          "reserved": false,
          "profile": "generic",
          "verdict": "skip",
          "reason": "ticket bajo (<10€), envío mata margen"
        },
        {
          "title": "Airpods 4 ANC Nuevos",
          "price": 135,
          "city": "Madrid",
          "url": "https://es.wallapop.com/item/airpods-4-anc-nuevos-1255848477",
          "reserved": false,
          "profile": "generic",
          "query_ebay": "airpods anc nuevos",
          "verdict": "skip",
          "reason": "0 reservados de 'airpods anc nuevos' (sin evidencia de demanda)"
        },
        {
          "title": "Airpods Pro 3 Blancos",
          "price": 130,
          "city": "Roses",
          "url": "https://es.wallapop.com/item/airpods-pro-3-blancos-1255848099",
          "reserved": false,
          "profile": "generic",
          "query_ebay": "airpods pro blancos",
          "verdict": "skip",
          "reason": "130€ vs mín reservado 18€ (margen <30%, no es ganga clara)"
        },
        {
          "title": "Airpods Pro 3",
          "price": 150,
          "city": "Massafra",
          "url": "https://es.wallapop.com/item/airpods-pro-3-1255848045",
          "reserved": false,
          "profile": "generic",
          "query_ebay": "airpods pro",
          "verdict": "skip",
          "reason": "150€ vs mín reservado 18€ (margen <30%, no es ganga clara)"
        },
        {
          "title": "Airpods Max Azul",
          "price": 250,
          "city": "Madrid",
          "url": "https://es.wallapop.com/item/airpods-max-azul-1255847651",
          "reserved": false,
          "profile": "generic",
          "query_ebay": "airpods max azul",
          "verdict": "skip",
          "reason": "0 reservados de 'airpods max azul' (sin evidencia de demanda)"
        },
        {
          "title": "Airpods Apple Blancos tienen",
          "price": 30,
          "city": "Zaragoza",
          "url": "https://es.wallapop.com/item/airpods-apple-blancos-tienen-1255847480",
          "reserved": false,
          "profile": "generic",
          "query_ebay": "airpods apple blancos tienen",
          "verdict": "skip",
          "reason": "30€ vs mín reservado 18€ (margen <30%, no es ganga clara)"
        },
        {
          "title": "Airpods Pro 3 Apple OG iPhone (nuevo)",
          "price": 59.95,
          "city": "Barcelona",
          "url": "https://es.wallapop.com/item/airpods-pro-3-apple-og-iphone-nuevo-1255846777",
          "reserved": false,
          "profile": "generic",
          "query_ebay": "airpods pro apple iphone (nuevo)",
          "verdict": "skip",
          "reason": "0 reservados de 'airpods pro apple iphone (nuevo)' (sin evidencia de demanda)"
        },
        {
          "title": "Estuche de Carga AirPods Pro 2ª Gen",
          "price": 90,
          "city": "Mataró",
          "url": "https://es.wallapop.com/item/estuche-de-carga-airpods-pro-2-gen-1255846537",
          "reserved": false,
          "profile": "generic",
          "query_ebay": "estuche carga airpods pro gen",
          "verdict": "skip",
          "reason": "0 reservados de 'estuche carga airpods pro gen' (sin evidencia de demanda)"
        },
        {
          "title": "Funda AirPods 2ª Gen - Diseño Enojado",
          "price": 3,
          "city": "Madrid",
          "url": "https://es.wallapop.com/item/funda-airpods-2-gen-diseno-enojado-1255845589",
          "reserved": false,
          "profile": "generic",
          "verdict": "skip",
          "reason": "ticket bajo (<10€), envío mata margen"
        },
        {
          "title": "Apple AirPods 2 Carga Inalámbrica",
          "price": 20,
          "city": "Madrid",
          "url": "https://es.wallapop.com/item/apple-airpods-2-carga-inalambrica-1255843749",
          "reserved": false,
          "profile": "generic",
          "query_ebay": "apple airpods carga inalambrica",
          "verdict": "skip",
          "reason": "0 reservados de 'apple airpods carga inalambrica' (sin evidencia de demanda)"
        },
        {
          "title": "AirPo",
          "price": 60,
          "city": "Granollers",
          "url": "https://es.wallapop.com/item/airpo-1255842683",
          "reserved": false,
          "profile": "generic",
          "query_ebay": "airpo",
          "verdict": "skip",
          "reason": "0 reservados de 'airpo' (sin evidencia de demanda)"
        },
        {
          "title": "iPhone 13 Pro 128GB ; Bateria 100%",
          "price": 329.99,
          "city": "Granada",
          "url": "https://es.wallapop.com/item/iphone-13-pro-128gb-bateria-100-1255848450",
          "reserved": false,
          "profile": "generic",
          "query_ebay": "iphone pro 128gb bateria 100%",
          "verdict": "skip",
          "reason": "0 reservados de 'iphone pro 128gb bateria 100%' (sin evidencia de demanda)"
        },
        {
          "title": "iPhone 17 Pro Max 256GB Naranja Sin Abrir",
          "price": 1250,
          "city": "Petrer",
          "url": "https://es.wallapop.com/item/iphone-17-pro-max-256gb-naranja-sin-abrir-1255848047",
          "reserved": false,
          "profile": "generic",
          "query_ebay": "iphone pro max 256gb naranja",
          "verdict": "skip",
          "reason": "1250€ vs mín reservado 1199€ (margen <30%, no es ganga clara)"
        },
        {
          "title": "iPhone 16 Pro 256GB Plata",
          "price": 600,
          "city": "Torrevieja",
          "url": "https://es.wallapop.com/item/iphone-16-pro-256gb-plata-1255847812",
          "reserved": false,
          "profile": "generic",
          "query_ebay": "iphone pro 256gb plata",
          "verdict": "skip",
          "reason": "0 reservados de 'iphone pro 256gb plata' (sin evidencia de demanda)"
        },
        {
          "title": "APPLE WATCH SERIES 11 46MM NEGRO PRECINTADO",
          "price": 449,
          "city": "Valencia",
          "url": "https://es.wallapop.com/item/apple-watch-series-11-46mm-negro-precintado-1255847640",
          "reserved": false,
          "profile": "generic",
          "query_ebay": "apple watch series 46mm negro",
          "verdict": "skip",
          "reason": "0 reservados de 'apple watch series 46mm negro' (sin evidencia de demanda)"
        },
        {
          "title": "IPHONE 12 PRO MAX 256GB GRAFITO 95% BATERIA",
          "price": 369,
          "city": "Valencia",
          "url": "https://es.wallapop.com/item/iphone-12-pro-max-256gb-grafito-95-bateria-1255847578",
          "reserved": false,
          "profile": "generic",
          "query_ebay": "iphone pro max 256gb grafito",
          "verdict": "skip",
          "reason": "0 reservados de 'iphone pro max 256gb grafito' (sin evidencia de demanda)"
        },
        {
          "title": "IPHONE 14 PLUS 128GB NEGRO 100% BATERIA",
          "price": 379,
          "city": "Valencia",
          "url": "https://es.wallapop.com/item/iphone-14-plus-128gb-negro-100-bateria-1255847517",
          "reserved": false,
          "profile": "generic",
          "query_ebay": "iphone plus 128gb negro 100%",
          "verdict": "skip",
          "reason": "0 reservados de 'iphone plus 128gb negro 100%' (sin evidencia de demanda)"
        },
        {
          "title": "SAMSUNG S23 ULTRA 512GB NEGRO",
          "price": 539,
          "city": "Valencia",
          "url": "https://es.wallapop.com/item/samsung-s23-ultra-512gb-negro-1255847463",
          "reserved": false,
          "profile": "generic",
          "query_ebay": "samsung s23 ultra 512gb negro",
          "verdict": "skip",
          "reason": "0 reservados de 'samsung s23 ultra 512gb negro' (sin evidencia de demanda)"
        },
        {
          "title": "SAMSUNG S25 PLUS 512GB VERDE 99% BATERÍA",
          "price": 719,
          "city": "Valencia",
          "url": "https://es.wallapop.com/item/samsung-s25-plus-512gb-verde-99-bateria-1255847361",
          "reserved": false,
          "profile": "generic",
          "query_ebay": "samsung s25 plus 512gb verde",
          "verdict": "skip",
          "reason": "0 reservados de 'samsung s25 plus 512gb verde' (sin evidencia de demanda)"
        },
        {
          "title": "iPhone 14 Apple",
          "price": 350,
          "city": "La Mamola",
          "url": "https://es.wallapop.com/item/iphone-14-apple-1255847334",
          "reserved": false,
          "profile": "generic",
          "query_ebay": "iphone apple",
          "verdict": "skip",
          "reason": "0 reservados de 'iphone apple' (sin evidencia de demanda)"
        },
        {
          "title": "IPHONE 14 PRO MAX 256GB PLATA 100% BATERIA",
          "price": 639,
          "city": "Valencia",
          "url": "https://es.wallapop.com/item/iphone-14-pro-max-256gb-plata-100-bateria-1255847311",
          "reserved": false,
          "profile": "generic",
          "query_ebay": "iphone pro max 256gb plata",
          "ebay_count": 0,
          "ebay_price_estimate": 0,
          "margin_net": 405.5,
          "margin_pct": 63,
          "score": 75,
          "from_cache": false,
          "verdict": "SIGNAL"
        },
        {
          "title": "iPhone 15 128GB Rosa ; Bateria 89%",
          "price": 419.99,
          "city": "Granada",
          "url": "https://es.wallapop.com/item/iphone-15-128gb-rosa-bateria-89-1255847226",
          "reserved": false,
          "profile": "generic",
          "query_ebay": "iphone 128gb rosa bateria 89%",
          "verdict": "skip",
          "reason": "0 reservados de 'iphone 128gb rosa bateria 89%' (sin evidencia de demanda)"
        },
        {
          "title": "IPHONE SE 2020 128GB NEGRO 100% BATERIA -.-.",
          "price": 149,
          "city": "Valencia",
          "url": "https://es.wallapop.com/item/iphone-se-2020-128gb-negro-100-bateria-1255847209",
          "reserved": false,
          "profile": "generic",
          "query_ebay": "iphone 128gb negro 100% bateria",
          "verdict": "skip",
          "reason": "0 reservados de 'iphone 128gb negro 100% bateria' (sin evidencia de demanda)"
        },
        {
          "title": "iPhone 16 Rosa",
          "price": 520,
          "city": "Leganés",
          "url": "https://es.wallapop.com/item/iphone-16-rosa-1255847175",
          "reserved": false,
          "profile": "generic",
          "query_ebay": "iphone rosa",
          "verdict": "skip",
          "reason": "0 reservados de 'iphone rosa' (sin evidencia de demanda)"
        },
        {
          "title": "iPhone 12 Mini Morado",
          "price": 120,
          "city": "Linares",
          "url": "https://es.wallapop.com/item/iphone-12-mini-morado-1255847055",
          "reserved": false,
          "profile": "generic",
          "query_ebay": "iphone mini morado",
          "verdict": "skip",
          "reason": "0 reservados de 'iphone mini morado' (sin evidencia de demanda)"
        },
        {
          "title": "IPHONE 13 MINI 128GB ROSA 100% BATERIA - 0 ciclos",
          "price": 329,
          "city": "Valencia",
          "url": "https://es.wallapop.com/item/iphone-13-mini-128gb-rosa-100-bateria-0-ciclos-1255847029",
          "reserved": false,
          "profile": "generic",
          "query_ebay": "iphone mini 128gb rosa 100%",
          "verdict": "skip",
          "reason": "0 reservados de 'iphone mini 128gb rosa 100%' (sin evidencia de demanda)"
        },
        {
          "title": "iPhone 11 64GB Negro",
          "price": 70,
          "city": "Barcelona",
          "url": "https://es.wallapop.com/item/iphone-11-64gb-negro-1255847008",
          "reserved": false,
          "profile": "generic",
          "verdict": "skip",
          "reason": "mal estado: grieta"
        },
        {
          "title": "iPhone 11 128GB Morado Para reparar o piezas",
          "price": 35,
          "city": "Alicante/Alacant",
          "url": "https://es.wallapop.com/item/iphone-11-128gb-morado-para-reparar-o-piezas-1255847001",
          "reserved": false,
          "profile": "generic",
          "verdict": "skip",
          "reason": "mal estado: rota"
        },
        {
          "title": "IPHONE 15 PRO 128GB BLANCO 100% BATERIA",
          "price": 659,
          "city": "Valencia",
          "url": "https://es.wallapop.com/item/iphone-15-pro-128gb-blanco-100-bateria-1255846886",
          "reserved": false,
          "profile": "generic",
          "query_ebay": "iphone pro 128gb blanco 100%",
          "verdict": "skip",
          "reason": "0 reservados de 'iphone pro 128gb blanco 100%' (sin evidencia de demanda)"
        },
        {
          "title": "IPHONE 15 PLUS 128GB NEGRO 88% BATERÍA",
          "price": 509,
          "city": "Valencia",
          "url": "https://es.wallapop.com/item/iphone-15-plus-128gb-negro-88-bateria-1255846826",
          "reserved": false,
          "profile": "generic",
          "query_ebay": "iphone plus 128gb negro 88%",
          "verdict": "skip",
          "reason": "0 reservados de 'iphone plus 128gb negro 88%' (sin evidencia de demanda)"
        },
        {
          "title": "iPhone 13 mini blanco",
          "price": 300,
          "city": "Corralejo",
          "url": "https://es.wallapop.com/item/iphone-13-mini-blanco-1255846729",
          "reserved": false,
          "profile": "generic",
          "query_ebay": "iphone mini blanco",
          "verdict": "skip",
          "reason": "300€ vs mín reservado 55€ (margen <30%, no es ganga clara)"
        },
        {
          "title": "iPhone 6S Rose Gold",
          "price": 35,
          "city": "Corrales",
          "url": "https://es.wallapop.com/item/iphone-6s-rose-gold-1255846721",
          "reserved": false,
          "profile": "generic",
          "verdict": "skip",
          "reason": "mal estado: no funciona"
        },
        {
          "title": "OPPO FIND X9 512GB NEGRO",
          "price": 749,
          "city": "Valencia",
          "url": "https://es.wallapop.com/item/oppo-find-x9-512gb-negro-1255846632",
          "reserved": false,
          "profile": "generic",
          "query_ebay": "oppo find 512gb negro",
          "verdict": "skip",
          "reason": "0 reservados de 'oppo find 512gb negro' (sin evidencia de demanda)"
        },
        {
          "title": "IPHONE 16 PRO 256GB DESERT 95% BATERÍA",
          "price": 869,
          "city": "Valencia",
          "url": "https://es.wallapop.com/item/iphone-16-pro-256gb-desert-95-bateria-1255846582",
          "reserved": false,
          "profile": "generic",
          "query_ebay": "iphone pro 256gb desert 95%",
          "verdict": "skip",
          "reason": "0 reservados de 'iphone pro 256gb desert 95%' (sin evidencia de demanda)"
        },
        {
          "title": "IPHONE 13 MINI 128GB BLANCO 93% BATERIA",
          "price": 289,
          "city": "Valencia",
          "url": "https://es.wallapop.com/item/iphone-13-mini-128gb-blanco-93-bateria-1255846488",
          "reserved": false,
          "profile": "generic",
          "query_ebay": "iphone mini 128gb blanco 93%",
          "verdict": "skip",
          "reason": "0 reservados de 'iphone mini 128gb blanco 93%' (sin evidencia de demanda)"
        },
        {
          "title": "IPHONE 12 128GB BLANCO 100% BATERIA",
          "price": 299,
          "city": "Valencia",
          "url": "https://es.wallapop.com/item/iphone-12-128gb-blanco-100-bateria-1255846452",
          "reserved": false,
          "profile": "generic",
          "query_ebay": "iphone 128gb blanco 100% bateria",
          "verdict": "skip",
          "reason": "0 reservados de 'iphone 128gb blanco 100% bateria' (sin evidencia de demanda)"
        },
        {
          "title": "iPhone 17 Pro Max 512GB Naranja",
          "price": 1200,
          "city": "Torrevieja",
          "url": "https://es.wallapop.com/item/iphone-17-pro-max-512gb-naranja-1255846424",
          "reserved": false,
          "profile": "generic",
          "query_ebay": "iphone pro max 512gb naranja",
          "verdict": "skip",
          "reason": "0 reservados de 'iphone pro max 512gb naranja' (sin evidencia de demanda)"
        },
        {
          "title": "IPHONE 14 128GB MALVA 100% BATERIA",
          "price": 399,
          "city": "Valencia",
          "url": "https://es.wallapop.com/item/iphone-14-128gb-malva-100-bateria-1255846402",
          "reserved": false,
          "profile": "generic",
          "query_ebay": "iphone 128gb malva 100% bateria",
          "verdict": "skip",
          "reason": "0 reservados de 'iphone 128gb malva 100% bateria' (sin evidencia de demanda)"
        },
        {
          "title": "iPhone 17 Pro Max",
          "price": 1060,
          "city": "Fuenlabrada",
          "url": "https://es.wallapop.com/item/iphone-17-pro-max-1255846398",
          "reserved": false,
          "profile": "generic",
          "query_ebay": "iphone pro max",
          "verdict": "skip",
          "reason": "0 reservados de 'iphone pro max' (sin evidencia de demanda)"
        },
        {
          "title": "IPHONE 14 PLUS 256GB BLANCO 100% BATERIA",
          "price": 479,
          "city": "Valencia",
          "url": "https://es.wallapop.com/item/iphone-14-plus-256gb-blanco-100-bateria-1255846283",
          "reserved": false,
          "profile": "generic",
          "query_ebay": "iphone plus 256gb blanco 100%",
          "verdict": "skip",
          "reason": "0 reservados de 'iphone plus 256gb blanco 100%' (sin evidencia de demanda)"
        },
        {
          "title": "HONOR MAGIC V2 512gb 16GB RAM MORADO PRECINTADO",
          "price": 599,
          "city": "Valencia",
          "url": "https://es.wallapop.com/item/honor-magic-v2-512gb-16gb-ram-morado-precintado-1255846242",
          "reserved": false,
          "profile": "generic",
          "query_ebay": "honor magic 512gb 16gb ram",
          "verdict": "skip",
          "reason": "0 reservados de 'honor magic 512gb 16gb ram' (sin evidencia de demanda)"
        },
        {
          "title": "iPhone 16 Plus 128 GB Rosa",
          "price": 799,
          "city": "Madrid",
          "url": "https://es.wallapop.com/item/iphone-16-plus-128-gb-rosa-1255846188",
          "reserved": false,
          "profile": "generic",
          "query_ebay": "iphone plus rosa",
          "verdict": "skip",
          "reason": "0 reservados de 'iphone plus rosa' (sin evidencia de demanda)"
        },
        {
          "title": "Smartphone Apple iPhone 17 Pro 512GB. PRECINTADO!!",
          "price": 1299,
          "city": "Oviedo",
          "url": "https://es.wallapop.com/item/smartphone-apple-iphone-17-pro-512gb-precintado-1255845862",
          "reserved": false,
          "profile": "generic",
          "query_ebay": "smartphone apple iphone pro 512gb.",
          "verdict": "skip",
          "reason": "0 reservados de 'smartphone apple iphone pro 512gb.' (sin evidencia de demanda)"
        },
        {
          "title": "iPhone 14 128GB Azul",
          "price": 350,
          "city": "Valencia",
          "url": "https://es.wallapop.com/item/iphone-14-128gb-azul-1255845832",
          "reserved": false,
          "profile": "generic",
          "query_ebay": "iphone 128gb azul",
          "verdict": "skip",
          "reason": "350€ vs mín reservado 200€ (margen <30%, no es ganga clara)"
        },
        {
          "title": "iPhone 15 Pro 1TB Space Gray",
          "price": 620,
          "city": "Sant Joan d'Alacant",
          "url": "https://es.wallapop.com/item/iphone-15-pro-1tb-space-gray-1255845820",
          "reserved": false,
          "profile": "generic",
          "query_ebay": "iphone pro 1tb space gray",
          "verdict": "skip",
          "reason": "0 reservados de 'iphone pro 1tb space gray' (sin evidencia de demanda)"
        },
        {
          "title": "iPhone 16 Pro 256GB Negro Titanio ciclos 0",
          "price": 795,
          "city": "Valencia",
          "url": "https://es.wallapop.com/item/iphone-16-pro-256gb-negro-titanio-ciclos-0-1255845472",
          "reserved": false,
          "profile": "generic",
          "query_ebay": "iphone pro 256gb negro titanio",
          "verdict": "skip",
          "reason": "0 reservados de 'iphone pro 256gb negro titanio' (sin evidencia de demanda)"
        },
        {
          "title": "iPhone 11 128GB Negro",
          "price": 120,
          "city": "Fuenlabrada",
          "url": "https://es.wallapop.com/item/iphone-11-128gb-negro-1255845379",
          "reserved": false,
          "profile": "generic",
          "query_ebay": "iphone 128gb negro",
          "verdict": "skip",
          "reason": "activos saturados (mín activo 149€ vs mín reservado 400€)"
        },
        {
          "title": "Funda iPhone 17 Pro - (NARANJA)",
          "price": 10,
          "city": "Castellbisbal",
          "url": "https://es.wallapop.com/item/funda-iphone-17-pro-naranja-1255845373",
          "reserved": false,
          "profile": "generic",
          "query_ebay": "funda iphone pro (naranja)",
          "verdict": "skip",
          "reason": "0 reservados de 'funda iphone pro (naranja)' (sin evidencia de demanda)"
        },
        {
          "title": "CAMBIO Samsung S25 Ultra 512GB Negro",
          "price": 0,
          "city": "Barcelona",
          "url": "https://es.wallapop.com/item/cambio-samsung-s25-ultra-512gb-negro-1255845274",
          "reserved": false,
          "verdict": "skip",
          "reason": "precio < 3€ (truco SEO)"
        },
        {
          "title": "Cable Appel de carga usb-c Watch original",
          "price": 13,
          "city": "Las Rozas de Madrid",
          "url": "https://es.wallapop.com/item/cable-appel-de-carga-usb-c-watch-original-1255848042",
          "reserved": false,
          "profile": "generic",
          "query_ebay": "cable appel carga usb-c watch",
          "verdict": "skip",
          "reason": "0 reservados de 'cable appel carga usb-c watch' (sin evidencia de demanda)"
        },
        {
          "title": "Cargador Portátil Power Bank Samsung Smartwatch",
          "price": 15,
          "city": "Madrid",
          "url": "https://es.wallapop.com/item/cargador-portatil-power-bank-samsung-smartwatch-1255847627",
          "reserved": false,
          "profile": "generic",
          "query_ebay": "cargador portatil power bank samsung",
          "verdict": "skip",
          "reason": "0 reservados de 'cargador portatil power bank samsung' (sin evidencia de demanda)"
        },
        {
          "title": "Apple Watch Series 8 45mm Plata - Batería 94%",
          "price": 185,
          "city": "Sant Sadurní d'Anoia",
          "url": "https://es.wallapop.com/item/apple-watch-series-8-45mm-plata-bateria-94-1255845534",
          "reserved": false,
          "profile": "generic",
          "query_ebay": "apple watch series 45mm plata",
          "verdict": "skip",
          "reason": "0 reservados de 'apple watch series 45mm plata' (sin evidencia de demanda)"
        },
        {
          "title": "Cargador inalámbrico Apple Watch",
          "price": 15,
          "city": "Lleida",
          "url": "https://es.wallapop.com/item/cargador-inalambrico-apple-watch-1255845518",
          "reserved": false,
          "profile": "generic",
          "query_ebay": "cargador inalambrico apple watch",
          "verdict": "skip",
          "reason": "0 reservados de 'cargador inalambrico apple watch' (sin evidencia de demanda)"
        },
        {
          "title": "Correa Nike Sport Loop Pride Edition",
          "price": 20,
          "city": "Cerdanyola del Vallès",
          "url": "https://es.wallapop.com/item/correa-nike-sport-loop-pride-edition-1255845309",
          "reserved": false,
          "profile": "generic",
          "query_ebay": "correa nike sport loop pride",
          "verdict": "skip",
          "reason": "0 reservados de 'correa nike sport loop pride' (sin evidencia de demanda)"
        },
        {
          "title": "Apple Watch Series 10 42mm GPS Rosa",
          "price": 219,
          "city": "Trezzano sul Naviglio",
          "url": "https://es.wallapop.com/item/apple-watch-series-10-42mm-gps-rosa-1255844740",
          "reserved": false,
          "profile": "generic",
          "verdict": "skip",
          "reason": "posible fake: no original"
        },
        {
          "title": "Apple Watch Series 7 45mm",
          "price": 150,
          "city": "Barcelona",
          "url": "https://es.wallapop.com/item/apple-watch-series-7-45mm-1255844087",
          "reserved": false,
          "profile": "generic",
          "query_ebay": "apple watch series 45mm",
          "verdict": "skip",
          "reason": "150€ vs mín reservado 150€ (margen <30%, no es ganga clara)"
        },
        {
          "title": "Apple Watch Ultra 2 GPS+LTE Titanio",
          "price": 550,
          "city": "Doneztebe",
          "url": "https://es.wallapop.com/item/apple-watch-ultra-2-gps-lte-titanio-1255843801",
          "reserved": false,
          "profile": "generic",
          "query_ebay": "apple watch ultra gps+lte titanio",
          "verdict": "skip",
          "reason": "0 reservados de 'apple watch ultra gps+lte titanio' (sin evidencia de demanda)"
        },
        {
          "title": "Apple Watch SE 2ª gen 40mm celular LTE Plata",
          "price": 149,
          "city": "Trezzano sul Naviglio",
          "url": "https://es.wallapop.com/item/apple-watch-se-2-gen-40mm-cellular-lte-argento-1255843164",
          "reserved": false,
          "profile": "generic",
          "verdict": "skip",
          "reason": "posible fake: no original"
        }
      ],
      "signals": 1
    },
    "Cine, libros y música": {
      "total_items": 169,
      "new_items": 22,
      "items": [
        {
          "title": "Mozart Sinfonie LP Great Performances",
          "price": 30,
          "city": "Anagni",
          "url": "https://es.wallapop.com/item/mozart-sinfonie-lp-great-performances-1255848297",
          "reserved": false,
          "profile": "vinilo",
          "query_ebay": "mozart sinfonie great performances",
          "verdict": "skip",
          "reason": "0 reservados de 'mozart sinfonie great performances' (sin evidencia de demanda)"
        },
        {
          "title": "Vinilo Doble Lp Mecano 20 Grandes Canciones",
          "price": 12,
          "city": "Barcelona",
          "url": "https://es.wallapop.com/item/vinilo-doble-lp-mecano-20-grandes-canciones-1255847356",
          "reserved": false,
          "profile": "vinilo",
          "query_ebay": "doble mecano grandes canciones",
          "verdict": "skip",
          "reason": "0 reservados de 'doble mecano grandes canciones' (sin evidencia de demanda)"
        },
        {
          "title": "Mozart - Los 4 Últimos Conciertos Para Piano LP",
          "price": 20,
          "city": "Anagni",
          "url": "https://es.wallapop.com/item/mozart-i-4-ultimi-concerti-per-pianoforte-lp-1255846807",
          "reserved": false,
          "profile": "vinilo",
          "query_ebay": "mozart los ultimos conciertos para",
          "verdict": "skip",
          "reason": "0 reservados de 'mozart los ultimos conciertos para' (sin evidencia de demanda)"
        },
        {
          "title": "LP Lolita Valderrama - Arte, Duende y Sentimiento",
          "price": 6,
          "city": "Arroyo de La Miel",
          "url": "https://es.wallapop.com/item/lp-lolita-valderrama-arte-duende-y-sentimiento-1255846503",
          "reserved": false,
          "profile": "vinilo",
          "query_ebay": "lolita valderrama arte, duende sentimiento",
          "verdict": "skip",
          "reason": "0 reservados de 'lolita valderrama arte, duende sentimiento' (sin evidencia de demanda)"
        },
        {
          "title": "ABBA - The Visitors | Vinilo LP",
          "price": 14.9,
          "city": "Toledo",
          "url": "https://es.wallapop.com/item/abba-the-visitors-vinilo-lp-1255846339",
          "reserved": false,
          "profile": "vinilo",
          "verdict": "skip",
          "reason": "vinilo problema: salto"
        },
        {
          "title": "Judas Priest Live in Los Angeles '90 Vinilo RSD LP",
          "price": 39.99,
          "city": "Valladolid",
          "url": "https://es.wallapop.com/item/judas-priest-live-in-los-angeles-90-vinilo-rsd-lp-1255846085",
          "reserved": false,
          "profile": "vinilo",
          "query_ebay": "judas priest live los angeles",
          "verdict": "skip",
          "reason": "0 reservados de 'judas priest live los angeles' (sin evidencia de demanda)"
        },
        {
          "title": "Lote Vinilos Elvis y The Beatles",
          "price": 20,
          "city": "Madrid",
          "url": "https://es.wallapop.com/item/lote-vinilos-elvis-y-the-beatles-1255845707",
          "reserved": true,
          "profile": "vinilo",
          "verdict": "skip",
          "reason": "lote multi-disco, no evaluable"
        },
        {
          "title": "Bella Italia - Anema e Core LP",
          "price": 9.5,
          "city": "Brescia",
          "url": "https://es.wallapop.com/item/bella-italia-anema-e-core-lp-1255842481",
          "reserved": false,
          "profile": "vinilo",
          "verdict": "skip",
          "reason": "lote multi-disco, no evaluable"
        },
        {
          "title": "Bach: Cantatas Sacras 71 CD Colección Completa",
          "price": 700,
          "city": "Reus",
          "url": "https://es.wallapop.com/item/bach-cantatas-sacras-71-cd-coleccion-completa-1255842906",
          "reserved": false,
          "profile": "generic",
          "query_ebay": "bach: cantatas sacras completa",
          "verdict": "skip",
          "reason": "0 reservados de 'bach: cantatas sacras completa' (sin evidencia de demanda)"
        },
        {
          "title": "Lote 6 Blu-ray: Los Juegos, Elysium, Avatar 3D",
          "price": 25,
          "city": "Alcobendas",
          "url": "https://es.wallapop.com/item/lote-6-blu-ray-los-juegos-elysium-avatar-3d-1255847702",
          "reserved": false,
          "profile": "generic",
          "query_ebay": "blu-ray: los juegos, elysium, avatar",
          "verdict": "skip",
          "reason": "0 reservados de 'blu-ray: los juegos, elysium, avatar' (sin evidencia de demanda)"
        },
        {
          "title": "El Último Patriota Blu-ray",
          "price": 7.9,
          "city": "Barcelona",
          "url": "https://es.wallapop.com/item/el-ultimo-patriota-blu-ray-1255846863",
          "reserved": false,
          "profile": "generic",
          "verdict": "skip",
          "reason": "mal estado: rota"
        },
        {
          "title": "Dragon Ball Super Broly Edición Coleccionista Blu-",
          "price": 250,
          "city": "Madrid",
          "url": "https://es.wallapop.com/item/dragon-ball-super-broly-edicion-coleccionista-blu-1255844819",
          "reserved": false,
          "profile": "generic",
          "query_ebay": "dragon ball super broly edicion",
          "verdict": "skip",
          "reason": "0 reservados de 'dragon ball super broly edicion' (sin evidencia de demanda)"
        },
        {
          "title": "Blu-ray A Pistol for Ringo + The Return of Ringo",
          "price": 20,
          "city": "Granada",
          "url": "https://es.wallapop.com/item/blu-ray-a-pistol-for-ringo---the-return-of-ringo-1255844566",
          "reserved": false,
          "profile": "generic",
          "verdict": "skip",
          "reason": "mal estado: roto"
        },
        {
          "title": "El Sargento de Hierro Blu-ray",
          "price": 11.9,
          "city": "Barcelona",
          "url": "https://es.wallapop.com/item/el-sargento-de-hierro-blu-ray-1255844527",
          "reserved": false,
          "profile": "generic",
          "query_ebay": "sargento hierro blu-ray",
          "verdict": "skip",
          "reason": "0 reservados de 'sargento hierro blu-ray' (sin evidencia de demanda)"
        },
        {
          "title": "Dragon Ball Películas Blu-ray Deluxe Ed.",
          "price": 160,
          "city": "Madrid",
          "url": "https://es.wallapop.com/item/dragon-ball-peliculas-blu-ray-deluxe-ed-1255843228",
          "reserved": false,
          "profile": "generic",
          "query_ebay": "dragon ball peliculas blu-ray deluxe",
          "verdict": "skip",
          "reason": "0 reservados de 'dragon ball peliculas blu-ray deluxe' (sin evidencia de demanda)"
        },
        {
          "title": "My Hero Academia lote",
          "price": 20,
          "city": "Valladolid",
          "url": "https://es.wallapop.com/item/my-hero-academia-lote-1255842670",
          "reserved": false,
          "profile": "generic",
          "query_ebay": "hero academia",
          "verdict": "skip",
          "reason": "0 reservados de 'hero academia' (sin evidencia de demanda)"
        },
        {
          "title": "MS. MARVEL: FUERA DE LO NORMAL",
          "price": 7,
          "city": "El Perello",
          "url": "https://es.wallapop.com/item/ms-marvel-fuera-de-lo-normal-1255847433",
          "reserved": false,
          "profile": "vinilo",
          "verdict": "skip",
          "reason": "lote multi-disco, no evaluable"
        },
        {
          "title": "Ms. Marvel 1. Fuera De Lo Normal",
          "price": 6,
          "city": "Pozuelo de Alarcón",
          "url": "https://es.wallapop.com/item/ms-marvel-1-fuera-de-lo-normal-1255847283",
          "reserved": false,
          "profile": "generic",
          "verdict": "skip",
          "reason": "ticket bajo (<10€), envío mata margen"
        },
        {
          "title": "Máximo security",
          "price": 18,
          "city": "Alfafar",
          "url": "https://es.wallapop.com/item/maximo-security-1255845744",
          "reserved": false,
          "profile": "generic",
          "query_ebay": "maximo security",
          "verdict": "skip",
          "reason": "0 reservados de 'maximo security' (sin evidencia de demanda)"
        },
        {
          "title": "Pack de libros: Crímenes del circulo polar",
          "price": 25,
          "city": "Barcelona",
          "url": "https://es.wallapop.com/item/pack-de-libros-crimenes-del-circulo-polar-1255847436",
          "reserved": false,
          "profile": "generic",
          "query_ebay": "pack libros: crimenes del circulo",
          "verdict": "skip",
          "reason": "0 reservados de 'pack libros: crimenes del circulo' (sin evidencia de demanda)"
        },
        {
          "title": "Vuelo (Campaña edición limitada) (Trilogía Rave...",
          "price": 2.99,
          "city": "Peñiscola",
          "url": "https://es.wallapop.com/item/vuelo-campana-edicion-limitada-trilogia-rave-1255847392",
          "reserved": false,
          "verdict": "skip",
          "reason": "precio < 3€ (truco SEO)"
        },
        {
          "title": "Eragorn",
          "price": 6,
          "city": "Silla",
          "url": "https://es.wallapop.com/item/eragorn-1255843502",
          "reserved": false,
          "profile": "generic",
          "verdict": "skip",
          "reason": "ticket bajo (<10€), envío mata margen"
        }
      ],
      "signals": 0
    },
    "Deporte y ocio": {
      "total_items": 78,
      "new_items": 21,
      "items": [
        {
          "title": "Gloomhaven Juego de Mesa",
          "price": 70,
          "city": "Madrid",
          "url": "https://es.wallapop.com/item/gloomhaven-juego-de-mesa-1255848285",
          "reserved": false,
          "profile": "generic",
          "query_ebay": "gloomhaven juego mesa",
          "verdict": "skip",
          "reason": "0 reservados de 'gloomhaven juego mesa' (sin evidencia de demanda)"
        },
        {
          "title": "Inserto Nemesis Lockdown",
          "price": 32,
          "city": "Burgos",
          "url": "https://es.wallapop.com/item/inserto-nemesis-lockdown-1255848193",
          "reserved": false,
          "profile": "generic",
          "query_ebay": "inserto nemesis lockdown",
          "verdict": "skip",
          "reason": "0 reservados de 'inserto nemesis lockdown' (sin evidencia de demanda)"
        },
        {
          "title": "Juego de mesa Hickory Dickory",
          "price": 25,
          "city": "Madrid",
          "url": "https://es.wallapop.com/item/juego-de-mesa-hickory-dickory-1255848094",
          "reserved": false,
          "profile": "vinilo",
          "verdict": "skip",
          "reason": "estado: rota"
        },
        {
          "title": "Juego de mesa Noches de Sangre",
          "price": 10,
          "city": "Huesca",
          "url": "https://es.wallapop.com/item/juego-de-mesa-noches-de-sangre-1255847899",
          "reserved": false,
          "profile": "generic",
          "query_ebay": "juego mesa noches sangre",
          "verdict": "skip",
          "reason": "0 reservados de 'juego mesa noches sangre' (sin evidencia de demanda)"
        },
        {
          "title": "Reforest: Costa Noroeste – NUEVO PRECINTADO",
          "price": 11,
          "city": "Torremolinos",
          "url": "https://es.wallapop.com/item/reforest-costa-noroeste-nuevo-precintado-1255847611",
          "reserved": false,
          "profile": "generic",
          "query_ebay": "reforest: costa noroeste precintado",
          "verdict": "skip",
          "reason": "0 reservados de 'reforest: costa noroeste precintado' (sin evidencia de demanda)"
        },
        {
          "title": "Battle Masters Juego de Guerra",
          "price": 50,
          "city": "Fraga",
          "url": "https://es.wallapop.com/item/battle-masters-juego-de-guerra-1255846682",
          "reserved": false,
          "profile": "generic",
          "query_ebay": "battle masters juego guerra",
          "verdict": "skip",
          "reason": "0 reservados de 'battle masters juego guerra' (sin evidencia de demanda)"
        },
        {
          "title": "Precintado! Warhammer Fantasy Role Play LUSTRIA",
          "price": 28.9,
          "city": "Madrid",
          "url": "https://es.wallapop.com/item/precintado-warhammer-fantasy-role-play-lustria-1255846463",
          "reserved": false,
          "profile": "generic",
          "query_ebay": "precintado! warhammer fantasy role play",
          "verdict": "skip",
          "reason": "0 reservados de 'precintado! warhammer fantasy role play' (sin evidencia de demanda)"
        },
        {
          "title": "Juego de mesa Wake up, Cthulhu!",
          "price": 10,
          "city": "Huesca",
          "url": "https://es.wallapop.com/item/juego-de-mesa-wake-up-cthulhu-1255846461",
          "reserved": false,
          "profile": "generic",
          "query_ebay": "juego mesa wake up, cthulhu!",
          "verdict": "skip",
          "reason": "0 reservados de 'juego mesa wake up, cthulhu!' (sin evidencia de demanda)"
        },
        {
          "title": "Lost Cities Les Rivaux - Juego de Cartas",
          "price": 8,
          "city": "Lugo",
          "url": "https://es.wallapop.com/item/lost-cities-les-rivaux-juego-de-cartas-1255846385",
          "reserved": false,
          "profile": "generic",
          "verdict": "skip",
          "reason": "ticket bajo (<10€), envío mata margen"
        },
        {
          "title": "Lost Cities Roll & Write Juego de Mesa",
          "price": 5,
          "city": "Logroño",
          "url": "https://es.wallapop.com/item/lost-cities-roll-write-juego-de-mesa-1255846121",
          "reserved": false,
          "profile": "generic",
          "verdict": "skip",
          "reason": "ticket bajo (<10€), envío mata margen"
        },
        {
          "title": "Código Secreto: Regreso a Hogwarts - Nuevo",
          "price": 28.95,
          "city": "Torremolinos",
          "url": "https://es.wallapop.com/item/codigo-secreto-regreso-a-hogwarts-nuevo-1255845966",
          "reserved": false,
          "profile": "generic",
          "query_ebay": "codigo secreto: regreso hogwarts",
          "verdict": "skip",
          "reason": "0 reservados de 'codigo secreto: regreso hogwarts' (sin evidencia de demanda)"
        },
        {
          "title": "Juego de mesa Tuareg",
          "price": 8,
          "city": "Pozuelo de Alarcón",
          "url": "https://es.wallapop.com/item/juego-de-mesa-tuareg-1255845845",
          "reserved": false,
          "profile": "generic",
          "verdict": "skip",
          "reason": "ticket bajo (<10€), envío mata margen"
        },
        {
          "title": "This War of Mine + Expansiones + Fanmade",
          "price": 220,
          "city": "Valdemoro",
          "url": "https://es.wallapop.com/item/this-war-of-mine---expansiones---fanmade-1255845785",
          "reserved": false,
          "profile": "generic",
          "query_ebay": "this war mine expansiones fanmade",
          "verdict": "skip",
          "reason": "0 reservados de 'this war mine expansiones fanmade' (sin evidencia de demanda)"
        },
        {
          "title": "Caravana al Oeste + Escenario Cowboy Solitario",
          "price": 10,
          "city": "Lugo",
          "url": "https://es.wallapop.com/item/caravana-al-oeste---escenario-cowboy-solitario-1255845128",
          "reserved": false,
          "profile": "generic",
          "query_ebay": "caravana oeste escenario cowboy solitario",
          "verdict": "skip",
          "reason": "0 reservados de 'caravana oeste escenario cowboy solitario' (sin evidencia de demanda)"
        },
        {
          "title": "Español Reglamento Warhammer Old World Español",
          "price": 40,
          "city": "Alicante/Alacant",
          "url": "https://es.wallapop.com/item/reglamento-warhammer-old-world-espanol-1255845077",
          "reserved": false,
          "profile": "generic",
          "query_ebay": "espanol reglamento warhammer old world",
          "verdict": "skip",
          "reason": "0 reservados de 'espanol reglamento warhammer old world' (sin evidencia de demanda)"
        },
        {
          "title": "Juego de mesa Saqueadores",
          "price": 20,
          "city": "Almería",
          "url": "https://es.wallapop.com/item/juego-de-mesa-saqueadores-1255845062",
          "reserved": false,
          "profile": "generic",
          "query_ebay": "juego mesa saqueadores",
          "verdict": "skip",
          "reason": "0 reservados de 'juego mesa saqueadores' (sin evidencia de demanda)"
        },
        {
          "title": "Juego de cartas Land of Gods",
          "price": 7,
          "city": "Lugo",
          "url": "https://es.wallapop.com/item/juego-de-cartas-land-of-gods-1255844738",
          "reserved": false,
          "profile": "generic",
          "verdict": "skip",
          "reason": "ticket bajo (<10€), envío mata margen"
        },
        {
          "title": "Spoilers The Game",
          "price": 10,
          "city": "Lugo",
          "url": "https://es.wallapop.com/item/spoilers-the-game-1255844510",
          "reserved": false,
          "profile": "generic",
          "query_ebay": "spoilers the game",
          "verdict": "skip",
          "reason": "0 reservados de 'spoilers the game' (sin evidencia de demanda)"
        },
        {
          "title": "Raqueta de pádel Babolat Reveal",
          "price": 50,
          "city": "Madrid",
          "url": "https://es.wallapop.com/item/raqueta-de-padel-babolat-reveal-1255848384",
          "reserved": false,
          "profile": "generic",
          "query_ebay": "raqueta padel babolat reveal",
          "verdict": "skip",
          "reason": "0 reservados de 'raqueta padel babolat reveal' (sin evidencia de demanda)"
        },
        {
          "title": "Raqueta Yonex Vcore Pro 100 Grip 2 280g",
          "price": 90,
          "city": "Valencia",
          "url": "https://es.wallapop.com/item/raqueta-yonex-vcore-pro-100-grip-2-280g-1255847682",
          "reserved": false,
          "profile": "generic",
          "query_ebay": "raqueta yonex vcore pro grip",
          "verdict": "skip",
          "reason": "0 reservados de 'raqueta yonex vcore pro grip' (sin evidencia de demanda)"
        },
        {
          "title": "Lote 2 raquetas infantiles Artengo con funda",
          "price": 10,
          "city": "Berriz",
          "url": "https://es.wallapop.com/item/lote-2-raquetas-infantiles-artengo-con-funda-1255844246",
          "reserved": false,
          "profile": "generic",
          "query_ebay": "raquetas infantiles artengo con funda",
          "verdict": "skip",
          "reason": "0 reservados de 'raquetas infantiles artengo con funda' (sin evidencia de demanda)"
        }
      ],
      "signals": 0
    },
    "Niños y bebés": {
      "total_items": 42,
      "new_items": 0,
      "items": [],
      "signals": 0
    }
  },
  "total_items": 204,
  "total_signals": 1,
  "duration_s": 136
}